README.md
setup.py
dbfiles/__init__.py
dbfiles/compiler.py
dbfiles/counter.py
dbfiles/errors.py
dbfiles/json_inline.yaml
dbfiles/main.py
dbfiles/schema.py
dbfiles/schema.yaml
dbfiles.egg-info/PKG-INFO
dbfiles.egg-info/SOURCES.txt
dbfiles.egg-info/dependency_links.txt
dbfiles.egg-info/entry_points.txt
dbfiles.egg-info/requires.txt
dbfiles.egg-info/top_level.txt
dbfiles/items/__init__.py
dbfiles/items/csv_file.py
dbfiles/items/item.py
dbfiles/items/item_with_query.py
dbfiles/items/json_file.py
dbfiles/items/sql_file.py
dbfiles/items/sql_inline.py
dbfiles/items/yaml_file.py