Metadata-Version: 1.2
Name: dbfiles
Version: 0.2.2
Summary: dbfiles - util for compile you sql files, csv data files, yaml, json configuration into catalog of sql files
Home-page: https://github.com/stepan-perlov/dbfiles
Author: Stepan Perlov
Author-email: stepanperlov@gmail.com
License: MIT
Platform: linux
Requires-Python: >=3
